DiffLibExt/__init__.py
DiffLibExt/__version__.py
DiffLibExt/difflibext.py
robotframework_difflibext-0.0.6.dist-info/LICENSE
robotframework_difflibext-0.0.6.dist-info/METADATA
robotframework_difflibext-0.0.6.dist-info/WHEEL
robotframework_difflibext-0.0.6.dist-info/top_level.txt
robotframework_difflibext-0.0.6.dist-info/RECORD
